foliant/preprocessors/utils/__init__.py
foliant/preprocessors/utils/header_anchors.py
foliantcontrib.utils.header_anchors-1.0.4.dist-info/LICENSE
foliantcontrib.utils.header_anchors-1.0.4.dist-info/METADATA
foliantcontrib.utils.header_anchors-1.0.4.dist-info/WHEEL
foliantcontrib.utils.header_anchors-1.0.4.dist-info/top_level.txt
foliantcontrib.utils.header_anchors-1.0.4.dist-info/RECORD
