Metadata-Version: 2.1
Name: foliantcontrib.utils.header-anchors
Version: 1.0.4
Summary: Utils for converting headers to anchors for different backends
Home-page: https://github.com/foliant-docs/foliantcontrib.utils.header_anchors
Author: Daniil Minukhin
Author-email: ddddsa@gmail.com
License: MIT
Platform: any
Classifier: Development Status :: 5 - Production/Stable
Classifier: Environment :: Console
Classifier: Intended Audience :: Developers
Classifier: License :: OSI Approved :: MIT License
Classifier: Operating System :: OS Independent
Classifier: Programming Language :: Python
Classifier: Topic :: Documentation
Classifier: Topic :: Utilities
Requires-Dist: foliant (>=1.0.8)
